universityhack2018/__init__.py
universityhack2018/cli.py
universityhack2018/config.py
universityhack2018/feature_engineering.py
universityhack2018/prediction.py
universityhack2018/universityhack2018.py
universityhack2018/objects/categorical.pkl
universityhack2018/objects/data_types.pkl
universityhack2018/objects/dummies.pkl
universityhack2018/objects/fill_values.pkl
universityhack2018/objects/model.pkl
universityhack2018/objects/num_feats.pkl
universityhack2018/objects/remove.pkl
universityhack2018/objects/skewed_features.pkl
universityhack2018/objects/standard_scaler.pkl
universityhack2018/objects/top_corrs.pkl
universityhack2018-0.7.0.dist-info/DESCRIPTION.rst
universityhack2018-0.7.0.dist-info/METADATA
universityhack2018-0.7.0.dist-info/RECORD
universityhack2018-0.7.0.dist-info/WHEEL
universityhack2018-0.7.0.dist-info/entry_points.txt
universityhack2018-0.7.0.dist-info/metadata.json
universityhack2018-0.7.0.dist-info/top_level.txt
