Metadata-Version: 2.0
Name: universityhack2018
Version: 0.7.0
Summary: Package for Data Rhapsody's UniversityHack 2018 Challenge solution.
Home-page: https://github.com/cabadsanchez/universityhack2018
Author: Carlos Abad Sánchez
Author-email: c.abad.sanchez@gmail.com
License: MIT license
Keywords: universityhack2018
Platform: UNKNOWN
Classifier: Development Status :: 2 - Pre-Alpha
Classifier: Intended Audience :: Developers
Classifier: License :: OSI Approved :: MIT License
Classifier: Natural Language :: English
Classifier: Programming Language :: Python :: 2
Classifier: Programming Language :: Python :: 2.7
Classifier: Programming Language :: Python :: 3
Classifier: Programming Language :: Python :: 3.4
Classifier: Programming Language :: Python :: 3.5
Classifier: Programming Language :: Python :: 3.6
Requires-Dist: Click (>=6.0)
Requires-Dist: numpy
Requires-Dist: pandas
Requires-Dist: scikit-learn
Requires-Dist: scipy
Requires-Dist: pickleshare
Requires-Dist: xgboost
